viewcube/__init__.py
viewcube/config.py
viewcube/cubeviewer.py
viewcube/main.py
viewcube/rgbmpl.py
viewcube/sonicube.py
viewcube/utils.py
viewcube/version.py
viewcube/viewrss.py
viewcube-0.2.9.dist-info/METADATA
viewcube-0.2.9.dist-info/WHEEL
viewcube-0.2.9.dist-info/entry_points.txt
viewcube-0.2.9.dist-info/top_level.txt
viewcube-0.2.9.dist-info/RECORD
