Metadata-Version: 2.4
Name: ViewCube
Version: 0.2.9
Summary: Datacube visualization and sonification
Author-email: Ruben Garcia-Benito <rgb@iaa.es>
License: MIT
Project-URL: Documentation, https://viewcube.readthedocs.io
Project-URL: Source, https://github.com/rgbIAA/viewcube/
Keywords: Scientific,Astrophysics,Spectroscopy,Sonification
Classifier: Programming Language :: Python :: 3
Classifier: License :: OSI Approved :: MIT License
Classifier: Operating System :: OS Independent
Requires-Python: >=3.6
Requires-Dist: numpy
Requires-Dist: astropy
Provides-Extra: sonicube
Requires-Dist: hashlib; extra == "sonicube"
Requires-Dist: tensorflow; extra == "sonicube"
Requires-Dist: pythonosc; extra == "sonicube"
Requires-Dist: ctcsound; extra == "sonicube"
Requires-Dist: librosa; extra == "sonicube"
